{
  "productName": "Mithavai",
  "homepageURL": "https://mithavai.testpress.in/ ",
  "appId": "TestpressTechLabs.Mithavai",
  "macAppStoreId": "6745862112",
  "windowsStoreId": "9NZ9X9QJT5SQ",
  "author": "Testpress",
  "description": "The app offers a range of features including practice exams for subject-wise and topic-wise preparation, along with progress tracking through detailed analytics and scores. Users can access educational study videos, view running and upcoming content, and download videos for offline viewing. The analytics section provides comprehensive reports, including overall performance summaries and detailed individual reports for each exam. Additionally, the 'Your Report' section allows users to view exam results and track the percentage of video content watched, helping them monitor their progress and improve their performance. ",
  "provisioningProfile": "lmsdemoDistributionprovisionprofile.provisionprofile",
  "identity": "Testpress Tech Labs LLP (BHAB7LC35Y)",
  "publisherId": "CN=27270D5F-9226-4A37-BF69-03BF0033FD28",
  "publisherDisplayName": "Testpress Tech Labs"
}
